setup.py
udacity_binomial_gaussian_package/Binomialdistribution.py
udacity_binomial_gaussian_package/Gaussiandistribution.py
udacity_binomial_gaussian_package/Generaldistribution.py
udacity_binomial_gaussian_package/__init__.py
udacity_binomial_gaussian_package.egg-info/PKG-INFO
udacity_binomial_gaussian_package.egg-info/SOURCES.txt
udacity_binomial_gaussian_package.egg-info/dependency_links.txt
udacity_binomial_gaussian_package.egg-info/not-zip-safe
udacity_binomial_gaussian_package.egg-info/top_level.txt