Metadata-Version: 1.0
Name: udacity-binomial-gaussian-package
Version: 0.0.1
Summary: Binomial and Gaussian distributions
Home-page: UNKNOWN
Author: Saburi Yusuf
Author-email: sarboldipo80@gmail.com
License: UNKNOWN
Platform: UNKNOWN
